sbomgen/main.py
sbomgen/Parsers/conanParser.py
sbomgen/Parsers/dartParser.py
sbomgen/Parsers/dotnetParser.py
sbomgen/Parsers/gomodParser.py
sbomgen/Parsers/gradleGroovyParser.py
sbomgen/Parsers/gradlekotlinDSLParser.py
sbomgen/Parsers/mavenParser.py
sbomgen/Parsers/npmParser.py
sbomgen/Parsers/phpParser.py
sbomgen/Parsers/requirementsParser.py
sbomgen/Parsers/rubyParser.py
sbomgen/Parsers/rustParser.py
sbomgen/Parsers/swiftParser.py
sbomgen/Parsers/yarnParser.py
sbomgen/Utility/dependencyTree.py
sbomgen/Utility/helpers.py
sbomgen/Utility/zip.py
sbomgentwo-1.0.0.dist-info/License.txt
sbomgentwo-1.0.0.dist-info/METADATA
sbomgentwo-1.0.0.dist-info/WHEEL
sbomgentwo-1.0.0.dist-info/entry_points.txt
sbomgentwo-1.0.0.dist-info/top_level.txt
sbomgentwo-1.0.0.dist-info/RECORD
